<TextureAtlas imagePath="sprites.png">
	<SubTexture name="Kiryoku_00.png" x="496" y="216" width="45" height="67"/>
	<SubTexture name="Kiryoku_01.png" x="542" y="78" width="45" height="67"/>
	<SubTexture name="Kiryoku_02.png" x="495" y="78" width="45" height="67"/>
	<SubTexture name="Kiryoku_03.png" x="497" y="285" width="45" height="67"/>
	<SubTexture name="Kiryoku_04.png" x="496" y="147" width="45" height="67"/>
	<SubTexture name="Kiryoku_05.png" x="543" y="147" width="45" height="67"/>
	<SubTexture name="Kiryoku_06.png" x="544" y="0" width="42" height="49"/>
	<SubTexture name="Kiryoku_07.png" x="445" y="203" width="49" height="49"/>
	<SubTexture name="Kiryoku_08.png" x="321" y="377" width="57" height="48"/>
	<SubTexture name="Kiryoku_09.png" x="388" y="204" width="55" height="54"/>
	<SubTexture name="Kiryoku_10.png" x="544" y="300" width="43" height="52"/>
	<SubTexture name="Kiryoku_11.png" x="492" y="361" width="47" height="50"/>
	<SubTexture name="Kiryoku_12.png" x="389" y="260" width="53" height="47"/>
	<SubTexture name="Kiryoku_12b.png" x="443" y="309" width="52" height="50"/>
	<SubTexture name="Kiryoku_13.png" x="585" y="408" width="42" height="49"/>
	<SubTexture name="Kiryoku_14.png" x="443" y="152" width="49" height="49"/>
	<SubTexture name="Kiryoku_15.png" x="321" y="427" width="57" height="48"/>
	<SubTexture name="Kiryoku_16.png" x="385" y="84" width="55" height="54"/>
	<SubTexture name="Kiryoku_17.png" x="541" y="354" width="43" height="52"/>
	<SubTexture name="Kiryoku_18.png" x="445" y="254" width="47" height="50"/>
	<SubTexture name="Kiryoku_19.png" x="380" y="461" width="53" height="47"/>
	<SubTexture name="Kiryoku_19b.png" x="438" y="361" width="52" height="50"/>
	<SubTexture name="Kiryoku_20.png" x="588" y="0" width="35" height="54"/>
	<SubTexture name="Kiryoku_21.png" x="585" y="459" width="38" height="50"/>
	<SubTexture name="Kiryoku_22.png" x="435" y="461" width="52" height="39"/>
	<SubTexture name="Kiryoku_23.png" x="589" y="56" width="35" height="54"/>
	<SubTexture name="Kiryoku_24.png" x="586" y="354" width="38" height="50"/>
	<SubTexture name="Kiryoku_25.png" x="321" y="104" width="52" height="39"/>
	<SubTexture name="Kiryoku_26.png" x="544" y="216" width="45" height="82"/>
	<SubTexture name="Kiryoku_27.png" x="489" y="413" width="47" height="76"/>
	<SubTexture name="Kiryoku_28.png" x="94" y="108" width="77" height="50"/>
	<SubTexture name="Kiryoku_29.png" x="0" y="398" width="85" height="50"/>
	<SubTexture name="Kiryoku_30.png" x="321" y="324" width="66" height="51"/>
	<SubTexture name="Kiryoku_31.png" x="389" y="140" width="52" height="50"/>
	<SubTexture name="Kiryoku_32.png" x="0" y="342" width="89" height="54"/>
	<SubTexture name="Kiryoku_33.png" x="91" y="286" width="78" height="81"/>
	<SubTexture name="Kiryoku_34.png" x="87" y="398" width="84" height="47"/>
	<SubTexture name="Kiryoku_35.png" x="0" y="168" width="91" height="57"/>
	<SubTexture name="Kiryoku_36.png" x="0" y="56" width="92" height="54"/>
	<SubTexture name="Kiryoku_37.png" x="443" y="0" width="50" height="74"/>
	<SubTexture name="Kiryoku_38.png" x="318" y="148" width="69" height="54"/>
	<SubTexture name="Kiryoku_39.png" x="250" y="288" width="69" height="82"/>
	<SubTexture name="Kiryoku_40.png" x="173" y="404" width="72" height="72"/>
	<SubTexture name="Kiryoku_41.png" x="247" y="404" width="72" height="72"/>
	<SubTexture name="Kiryoku_42.png" x="173" y="105" width="72" height="72"/>
	<SubTexture name="Kiryoku_43.png" x="380" y="377" width="56" height="82"/>
	<SubTexture name="Kiryoku_44.png" x="538" y="413" width="45" height="82"/>
	<SubTexture name="Kiryoku_45.png" x="495" y="0" width="47" height="76"/>
	<SubTexture name="Kiryoku_46.png" x="94" y="56" width="77" height="50"/>
	<SubTexture name="Kiryoku_47.png" x="0" y="450" width="85" height="50"/>
	<SubTexture name="Kiryoku_48.png" x="321" y="271" width="66" height="51"/>
	<SubTexture name="Kiryoku_49.png" x="389" y="309" width="52" height="50"/>
	<SubTexture name="Kiryoku_50.png" x="0" y="286" width="89" height="54"/>
	<SubTexture name="Kiryoku_51.png" x="93" y="168" width="78" height="81"/>
	<SubTexture name="Kiryoku_52.png" x="87" y="447" width="84" height="47"/>
	<SubTexture name="Kiryoku_53.png" x="0" y="227" width="91" height="57"/>
	<SubTexture name="Kiryoku_54.png" x="0" y="112" width="92" height="54"/>
	<SubTexture name="Kiryoku_55.png" x="443" y="76" width="50" height="74"/>
	<SubTexture name="Kiryoku_56.png" x="248" y="232" width="69" height="54"/>
	<SubTexture name="Kiryoku_57.png" x="247" y="148" width="69" height="82"/>
	<SubTexture name="Kiryoku_58.png" x="173" y="31" width="72" height="72"/>
	<SubTexture name="Kiryoku_59.png" x="247" y="74" width="72" height="72"/>
	<SubTexture name="Kiryoku_60.png" x="247" y="0" width="72" height="72"/>
	<SubTexture name="Kiryoku_61.png" x="385" y="0" width="56" height="82"/>
	<SubTexture name="Kiryoku_62.png" x="0" y="0" width="151" height="54"/>
	<SubTexture name="Kiryoku_63.png" x="319" y="204" width="67" height="65"/>
	<SubTexture name="Kiryoku_64.png" x="173" y="210" width="70" height="29"/>
	<SubTexture name="Kiryoku_65.png" x="173" y="179" width="72" height="29"/>
	<SubTexture name="Kiryoku_66.png" x="172" y="251" width="74" height="29"/>
	<SubTexture name="Kiryoku_67.png" x="153" y="0" width="76" height="29"/>
	<SubTexture name="Kiryoku_68.png" x="93" y="251" width="77" height="29"/>
	<SubTexture name="Kiryoku_69.png" x="91" y="369" width="63" height="23"/>
	<SubTexture name="Kiryoku_70.png" x="173" y="478" width="63" height="23"/>
	<SubTexture name="Kiryoku_71.png" x="321" y="52" width="62" height="50"/>
	<SubTexture name="Kiryoku_72.png" x="321" y="0" width="62" height="50"/>
	<SubTexture name="Kiryoku_73.png" x="173" y="343" width="75" height="59"/>
	<SubTexture name="Kiryoku_74.png" x="171" y="282" width="75" height="59"/>
</TextureAtlas>